aiko_monitor/__init__.py
aiko_monitor/core.py
aiko_monitor/main.py
aiko_monitor/schema.py
aiko_monitor/send.py
aiko_monitor/integrations/__init__.py
aiko_monitor/integrations/fastapi.py
aiko_monitor/integrations/flask.py
aiko_monitor-0.0.18.dist-info/METADATA
aiko_monitor-0.0.18.dist-info/WHEEL
aiko_monitor-0.0.18.dist-info/top_level.txt
aiko_monitor-0.0.18.dist-info/RECORD
