Metadata-Version: 2.4
Name: aiko-monitor
Version: 0.0.18
Requires-Dist: httpx<1.0,>=0.27.0
Requires-Dist: pydantic<3.0,>=2.0
